aws_jsiisamples/jsii_code_samples/__init__.py
aws_jsiisamples/jsii_code_samples/py.typed
aws_jsiisamples/jsii_code_samples/_jsii/__init__.py
aws_jsiisamples/jsii_code_samples/_jsii/jsii-code-samples@1.7.0.jsii.tgz
aws_jsiisamples.jsii_code_samples-1.7.0.dist-info/METADATA
aws_jsiisamples.jsii_code_samples-1.7.0.dist-info/WHEEL
aws_jsiisamples.jsii_code_samples-1.7.0.dist-info/top_level.txt
aws_jsiisamples.jsii_code_samples-1.7.0.dist-info/RECORD
