Metadata-Version: 2.1
Name: aws-jsiisamples.jsii-code-samples
Version: 1.7.0
Summary: Code samples that accompany the AWS blog post on jsii
Home-page: https://github.com/aws-samples/jsii-code-samples#readme
Author: Hari Pachuveetil <pachuvee@amazon.com>
License: MIT-0
Project-URL: Source, https://github.com/aws-samples/jsii-code-samples.git
Platform: UNKNOWN
Classifier: Intended Audience :: Developers
Classifier: Operating System :: OS Independent
Classifier: Programming Language :: JavaScript
Classifier: Programming Language :: Python :: 3 :: Only
Classifier: Programming Language :: Python :: 3.6
Classifier: Programming Language :: Python :: 3.7
Classifier: Programming Language :: Python :: 3.8
Classifier: Typing :: Typed
Requires-Python: >=3.6
Requires-Dist: jsii (<2.0.0,>=1.5.0)
Requires-Dist: publication (>=0.0.3)
